hapc/__init__.py
hapc/core.py
hapc/cv.py
hapc/single.py
hapc/Release/hapc_core.cp38-win_amd64.pyd
hapc-0.2.1.dist-info/LICENSE
hapc-0.2.1.dist-info/METADATA
hapc-0.2.1.dist-info/WHEEL
hapc-0.2.1.dist-info/top_level.txt
hapc-0.2.1.dist-info/RECORD
