Metadata-Version: 2.1
Name: hapc
Version: 0.2.1
Summary: Highly Adaptive Principal Components
Home-page: https://github.com/meixide/hapc
Author: Carlos García Meixide
Author-email: Carlos García Meixide <cgmeixide@gmail.com>
License: MIT
Project-URL: Homepage, https://github.com/meixide/hapc
Project-URL: Documentation, https://github.com/meixide/hapc#readme
Project-URL: Repository, https://github.com/meixide/hapc.git
Project-URL: Issues, https://github.com/meixide/hapc/issues
Classifier: Programming Language :: Python :: 3
Classifier: Programming Language :: Python :: 3.8
Classifier: Programming Language :: Python :: 3.9
Classifier: Programming Language :: Python :: 3.10
Classifier: Programming Language :: Python :: 3.11
Classifier: Programming Language :: Python :: 3.12
Classifier: Operating System :: OS Independent
Requires-Python: >=3.8
License-File: LICENSE
Requires-Dist: numpy<2.3,>=1.24
Requires-Dist: scipy>=1.7
Requires-Dist: scikit-learn>=0.24
Provides-Extra: dev
Requires-Dist: pytest; extra == "dev"
Requires-Dist: pytest-cov; extra == "dev"
Requires-Dist: black; extra == "dev"
Requires-Dist: flake8; extra == "dev"
